mikan/__init__.py
mikan/adjective.py
mikan/base.py
mikan/combine.py
mikan/compound.py
mikan/counter.py
mikan/date.py
mikan/exceptions.py
mikan/number.py
mikan/reading.py
mikan/utils.py
mikan/verb.py
mikan/word.py
mikan/writing.py
mikan-0.2.0.dist-info/LICENSE
mikan-0.2.0.dist-info/METADATA
mikan-0.2.0.dist-info/WHEEL
mikan-0.2.0.dist-info/top_level.txt
mikan-0.2.0.dist-info/RECORD
