Metadata-Version: 2.1
Name: mikan
Version: 0.2.0
Summary: A Japanese language manipulation library
Home-page: https://github.com/dzzhvks94vd2/mikan
Author: dzzhvks94vd2
Author-email: dzzhvks94vd2@protonmail.com
License: MIT
Platform: UNKNOWN
Classifier: Development Status :: 3 - Alpha
Classifier: Intended Audience :: Developers
Classifier: License :: OSI Approved :: MIT License
Classifier: Natural Language :: Japanese
Classifier: Programming Language :: Python :: 3
Classifier: Programming Language :: Python :: 3.9
Classifier: Topic :: Software Development :: Libraries :: Python Modules
Requires-Python: >=3.9
